translit_me/__init__.py
translit_me/lang_tables.py
translit_me/main.py
translit_me/transliterator.py
translit_me/tests/testCharTrie.py
translit_me/tests/test_main.py
translit_me/tests/test_remove_vowels.py
translit_me/tests/test_transliterate.py
translit_me-1.3.dist-info/licenses/LICENSE.txt
translit_me-1.3.dist-info/METADATA
translit_me-1.3.dist-info/WHEEL
translit_me-1.3.dist-info/top_level.txt
translit_me-1.3.dist-info/RECORD
