Metadata-Version: 2.4
Name: translit_me
Version: 1.3
Summary: A transliteration service for Middle-Eastern languages. 
Author-email: Tomer Sagi <tsagi@cs.aau.dk>, Sinai Rusinek <sinai.rusinek@mail.huji.ac.il>, Moran Zaga <mzaga@Staff.haifa.ac.il>
License:    Copyright [2022] [University of Haifa]
Project-URL: Homepage, https://mehdie.org/
Project-URL: Bug Tracker, https://gitlab.com/m8417/hebrew-transliteration-service/-/issues
Classifier: Programming Language :: Python :: 3
Classifier: License :: OSI Approved :: Apache Software License
Classifier: Operating System :: OS Independent
Requires-Python: >=3.7
License-File: LICENSE.txt
Dynamic: license-file
